src/__init__.py
src/forms.py
src/models.py
src/urls.py
src/views.py
src/templates/success.html
src/templates/upload.html
xlsx_exporter-1.0.4.dist-info/METADATA
xlsx_exporter-1.0.4.dist-info/WHEEL
xlsx_exporter-1.0.4.dist-info/entry_points.txt
xlsx_exporter-1.0.4.dist-info/top_level.txt
xlsx_exporter-1.0.4.dist-info/RECORD
